SlyUWU/__init__.py
SlyUWU/uwurandom.py
SlyUWU-0.2.0.dist-info/LICENSE
SlyUWU-0.2.0.dist-info/METADATA
SlyUWU-0.2.0.dist-info/WHEEL
SlyUWU-0.2.0.dist-info/top_level.txt
SlyUWU-0.2.0.dist-info/RECORD
